intura_ai/__init__.py
intura_ai/__version__.py
intura_ai/callbacks/__init__.py
intura_ai/callbacks/UsageTrackCallback/__init__.py
intura_ai/client/__init__.py
intura_ai/client/config.py
intura_ai/experiments/__init__.py
intura_ai/experiments/chat_model_experiment/__init__.py
intura_ai/libs/wrappers/langchain_chat_model/__init__.py
intura_ai/libs/wrappers/langchain_chat_model/anthropic.py
intura_ai/libs/wrappers/langchain_chat_model/deepseek.py
intura_ai/libs/wrappers/langchain_chat_model/fireworks.py
intura_ai/libs/wrappers/langchain_chat_model/google_generative_ai.py
intura_ai/libs/wrappers/langchain_chat_model/intura.py
intura_ai/libs/wrappers/langchain_chat_model/ollama.py
intura_ai/libs/wrappers/langchain_chat_model/open_ai.py
intura_ai/libs/wrappers/langchain_chat_model/together.py
intura_ai/platform/__init__.py
intura_ai/platform/dashboard_platform.py
intura_ai/platform/domain/__init__.py
intura_ai/platform/domain/experiment.py
intura_ai/platform/domain/treatment.py
intura_ai/shared/domain/__init__.py
intura_ai/shared/domain/intura_response.py
intura_ai/shared/external/intura_api.py
intura_ai/shared/middlewares/__init__.py
intura_ai/shared/middlewares/validate_api_key.py
intura_ai/shared/utils/logging.py
intura_ai/shared/variables/api_host.py
intura_ai-0.0.7.1.dist-info/licenses/LICENSE
intura_ai-0.0.7.1.dist-info/METADATA
intura_ai-0.0.7.1.dist-info/WHEEL
intura_ai-0.0.7.1.dist-info/top_level.txt
intura_ai-0.0.7.1.dist-info/RECORD
