Metadata-Version: 2.4
Name: intura-ai
Version: 0.0.7.1
Summary: Intelligent Research and Experimentation AI for LLM experimentation production. ⚠️ This package is in BETA and under active development.
Author-email: Intura <developer@intura.co>
Project-URL: Homepage, https://github.com/intura-co/intura-ai
Project-URL: Bug Tracker, https://github.com/intura-co/intura-ai/issues
Project-URL: Documentation, https://github.com/intura-co/intura-ai/blob/main/README.md
Project-URL: Repository, https://github.com/intura-co/intura-ai
Classifier: Programming Language :: Python :: 3
Classifier: License :: OSI Approved :: MIT License
Classifier: Operating System :: OS Independent
Classifier: Development Status :: 4 - Beta
Classifier: Intended Audience :: Developers
Classifier: Topic :: Scientific/Engineering :: Artificial Intelligence
Requires-Python: >=3.10
License-File: LICENSE
Requires-Dist: requests>=2.26.0
Requires-Dist: langchain>=0.3.13
Requires-Dist: langchain-community>=0.3.13
Requires-Dist: pydantic>=2.9.2
Requires-Dist: langchain-openai>=0.3.12
Provides-Extra: dev
Requires-Dist: pytest>=7.0.0; extra == "dev"
Requires-Dist: black>=23.0.0; extra == "dev"
Requires-Dist: isort>=5.12.0; extra == "dev"
Requires-Dist: mypy>=1.0.0; extra == "dev"
Requires-Dist: flake8>=6.0.0; extra == "dev"
Requires-Dist: build>=0.10.0; extra == "dev"
Requires-Dist: twine>=4.0.0; extra == "dev"
Provides-Extra: all-langchain-partner
Requires-Dist: langchain-together; extra == "all-langchain-partner"
Requires-Dist: langchain-google-genai; extra == "all-langchain-partner"
Requires-Dist: langchain-deepseek; extra == "all-langchain-partner"
Requires-Dist: langchain-anthropic; extra == "all-langchain-partner"
Requires-Dist: langchain-openai; extra == "all-langchain-partner"
Requires-Dist: langchain-xai; extra == "all-langchain-partner"
Provides-Extra: together
Requires-Dist: langchain-together; extra == "together"
Provides-Extra: google-genai
Requires-Dist: langchain-google-genai; extra == "google-genai"
Provides-Extra: deepseek
Requires-Dist: langchain-deepseek; extra == "deepseek"
Provides-Extra: anthropic
Requires-Dist: langchain-anthropic; extra == "anthropic"
Provides-Extra: openai
Requires-Dist: langchain-openai; extra == "openai"
Provides-Extra: xai
Requires-Dist: langchain-xai; extra == "xai"
Dynamic: license-file
